django_celery_results/__init__.py
django_celery_results/admin.py
django_celery_results/apps.py
django_celery_results/managers.py
django_celery_results/models.py
django_celery_results/urls.py
django_celery_results/utils.py
django_celery_results/views.py
django_celery_results/backends/__init__.py
django_celery_results/backends/cache.py
django_celery_results/backends/database.py
django_celery_results/migrations/0001_initial.py
django_celery_results/migrations/__init__.py
dvadmin3_celery/__init__.py
dvadmin3_celery/admin.py
dvadmin3_celery/apps.py
dvadmin3_celery/settings.py
dvadmin3_celery/tasks.py
dvadmin3_celery/urls.py
dvadmin3_celery/fixtures/__init__.py
dvadmin3_celery/fixtures/init_menu.json
dvadmin3_celery/fixtures/initialize.py
dvadmin3_celery/views/__init__.py
dvadmin3_celery/views/crontab_schedule.py
dvadmin3_celery/views/interval_schedule.py
dvadmin3_celery/views/periodic_task.py
dvadmin3_celery/views/task.py
dvadmin3_celery/views/task_detail.py
dvadmin3_celery-3.1.7.dist-info/LICENSE
dvadmin3_celery-3.1.7.dist-info/METADATA
dvadmin3_celery-3.1.7.dist-info/WHEEL
dvadmin3_celery-3.1.7.dist-info/entry_points.txt
dvadmin3_celery-3.1.7.dist-info/top_level.txt
dvadmin3_celery-3.1.7.dist-info/RECORD
