Metadata-Version: 2.1
Name: dvadmin3-celery
Version: 3.1.7
Summary: 适用于 django3-vue-admin 的celery异步插件
Home-page: https://gitee.com/huge-dream/dvadmin3-celery
Author: DVAdmin
Author-email: liqiang@django-vue-admin.com
Classifier: Programming Language :: Python :: 3
Classifier: License :: OSI Approved :: MIT License
Classifier: Operating System :: OS Independent
Requires-Python: >=3.7, <4
License-File: LICENSE
Requires-Dist: django-celery-beat ==2.7.0
Requires-Dist: tenant-schemas-celery ==3.0.0
Requires-Dist: django-redis ==5.4.0
